MANIFEST.in
README.md
setup.cfg
setup.py
airsign/__init__.py
airsign/__main__.py
airsign/configuration.py
airsign/wallet.py
airsign.egg-info/PKG-INFO
airsign.egg-info/SOURCES.txt
airsign.egg-info/dependency_links.txt
airsign.egg-info/entry_points.txt
airsign.egg-info/requires.txt
airsign.egg-info/top_level.txt