Metadata-Version: 1.1
Name: airsign
Version: 0.0.2
Summary: Command line tool to interface with the BitShares network
Home-page: http://www.github.com/xeroc/airsign
Author: Fabian Schuh
Author-email: <Fabian@BitShares.eu>
License: UNKNOWN
Download-URL: https://github.com/xeroc/airsign/tarball/0.0.2
Keywords: bitshares,library,api,rpc,cli
Platform: UNKNOWN
Classifier: License :: OSI Approved :: MIT License
Classifier: Operating System :: OS Independent
Classifier: Programming Language :: Python :: 3
Classifier: Development Status :: 3 - Alpha
Classifier: Intended Audience :: Developers
